[
      {
        "item_id": "M001",
        "name": "Margherita Pizza",
        "category": "Pizza",
        "price": 800.99,
        "availability": true
      },
      {
        "item_id": "M002",
        "name": "Pepperoni Pizza",
        "category": "Pizza",
        "price": 1000.99,
        "availability": true
      },
      {
        "item_id": "M003",
        "name": "BBQ Chicken Pizza",
        "category": "Pizza",
        "price": 1100.99,
        "availability": true
      },
      {
        "item_id": "M004",
        "name": "Caesar Salad",
        "category": "Salad",
        "price": 600.99,
        "availability": true
      },
      {
        "item_id": "M005",
        "name": "Greek Salad",
        "category": "Salad",
        "price": 70.99,
        "availability": true
      },
      {
        "item_id": "M006",
        "name": "Grilled Chicken Sandwich",
        "category": "Sandwich",
        "price": 90.49,
        "availability": true
      },
      {
        "item_id": "M007",
        "name": "BLT Sandwich",
        "category": "Sandwich",
        "price": 80.49,
        "availability": true
      },
      {
        "item_id": "M008",
        "name": "Spaghetti Bolognese",
        "category": "Pasta",
        "price": 120.99,
        "availability": true
      },
      {
        "item_id": "M009",
        "name": "Chicken Alfredo",
        "category": "Pasta",
        "price": 130.99,
        "availability": true
      },
      {
        "item_id": "M010",
        "name": "Garlic Bread",
        "category": "Appetizer",
        "price": 30.99,
        "availability": true
      },
      {
        "item_id": "M011",
        "name": "French Fries",
        "category": "Appetizer",
        "price": 40.49,
        "availability": true
      },
      {
        "item_id": "M012",
        "name": "Buffalo Wings",
        "category": "Appetizer",
        "price": 80.99,
        "availability": true
      },
      {
        "item_id": "M013",
        "name": "Cheeseburger",
        "category": "Burger",
        "price": 90.99,
        "availability": true
      },
      {
        "item_id": "M014",
        "name": "Veggie Burger",
        "category": "Burger",
        "price": 80.99,
        "availability": true
      },
      {
        "item_id": "M015",
        "name": "Chocolate Cake",
        "category": "Dessert",
        "price": 50.99,
        "availability": true
      },
      {
        "item_id": "M016",
        "name": "Apple Pie",
        "category": "Dessert",
        "price": 40.99,
        "availability": true
      },
      {
        "item_id": "M017",
        "name": "Vanilla Ice Cream",
        "category": "Dessert",
        "price": 30.99,
        "availability": true
      },
      {
        "item_id": "M018",
        "name": "Latte",
        "category": "Beverage",
        "price": 30.99,
        "availability": true
      },
      {
        "item_id": "M019",
        "name": "Iced Coffee",
        "category": "Beverage",
        "price": 30.49,
        "availability": true
      },
      {
        "item_id": "M020",
        "name": "Lemonade",
        "category": "Beverage",
        "price": 20.99,
        "availability": true
      }
]
  
  
